vgram/__init__.py
vgram/main/__init__.py
vgram/main/algorithm/__init__.py
vgram/main/algorithm/int_dictionary.py
vgram/main/algorithm/stat_dictionary.py
vgram/main/algorithm/vgram_builder.py
vgram/main/application/__init__.py
vgram/main/application/learn.py
vgram/main/interfaces/__init__.py
vgram/main/interfaces/base_tokenizer.py
vgram/main/interfaces/coder.py
vgram/main/interfaces/splitter.py
vgram/main/interfaces/tokenizer.py
vgram/main/interfaces/vgram_applier.py
vgram/main/interfaces/vgram_tokenizer.py
vgram/test/__init__.py
vgram/test/algorithm/__init__.py
vgram/test/algorithm/test_int_dictionary.py
vgram/test/interfaces/__init__.py
vgram/test/interfaces/paper_scores.py
vgram/test/interfaces/test_vgram_tokenizer.py
vgram/test/interfaces/vgram_paper_scores.py
pyvgram-0.1.2.dist-info/LICENSE
pyvgram-0.1.2.dist-info/METADATA
pyvgram-0.1.2.dist-info/WHEEL
pyvgram-0.1.2.dist-info/top_level.txt
pyvgram-0.1.2.dist-info/RECORD
