Metadata-Version: 2.1
Name: pyvgram
Version: 0.1.2
Summary: VGram tokenization
Home-page: https://github.com/akhvorov/pyvgram
Author: Aleksandr Khvorov
Author-email: khvorov.aleksandr@gmail.com
License: UNKNOWN
Platform: UNKNOWN
Classifier: Programming Language :: Python :: 3
Classifier: License :: OSI Approved :: MIT License
Classifier: Operating System :: OS Independent
Requires-Python: >=3.6
